pyram/PyRAM.py
pyram/PyRAMmp.py
pyram/__init__.py
pyram/matrc.py
pyram/outpt.py
pyram/solve.py
pyram/Tests/TestPyRAM.py
pyram/Tests/TestPyRAMmp.py
pyram/Tests/TestPyRAMmp_Config.xml
pyram/Tests/__init__.py
pyram/Tests/tl_ref.line
pyram-1.3.0.dist-info/LICENSE.md
pyram-1.3.0.dist-info/METADATA
pyram-1.3.0.dist-info/WHEEL
pyram-1.3.0.dist-info/top_level.txt
pyram-1.3.0.dist-info/RECORD
